pyqt_responsive_label/__init__.py
pyqt_responsive_label/responsiveLabel.py
pyqt_responsive_label-0.0.3.dist-info/LICENSE
pyqt_responsive_label-0.0.3.dist-info/METADATA
pyqt_responsive_label-0.0.3.dist-info/WHEEL
pyqt_responsive_label-0.0.3.dist-info/top_level.txt
pyqt_responsive_label-0.0.3.dist-info/RECORD
