Metadata-Version: 2.1
Name: pyqt-responsive-label
Version: 0.0.3
Summary: PyQt QLabel which can resize the font responsively accordance with window's size change
Home-page: https://github.com/yjg30737/pyqt-responsive-label.git
Author: Jung Gyu Yoon
Author-email: yjg30737@gmail.com
License: MIT
License-File: LICENSE
Requires-Dist: PyQt5 (>=5.8)
